django_nlf/__init__.py
django_nlf/conf.py
django_nlf/types.py
django_nlf/utils.py
django_nlf/antlr/DjangoNLF.g4
django_nlf/antlr/__init__.py
django_nlf/antlr/error_listener.py
django_nlf/antlr/exceptions.py
django_nlf/antlr/language.py
django_nlf/antlr/listener.py
django_nlf/antlr/generated/DjangoNLF.interp
django_nlf/antlr/generated/DjangoNLF.tokens
django_nlf/antlr/generated/DjangoNLFLexer.interp
django_nlf/antlr/generated/DjangoNLFLexer.py
django_nlf/antlr/generated/DjangoNLFLexer.tokens
django_nlf/antlr/generated/DjangoNLFParser.py
django_nlf/antlr/generated/__init__.py
django_nlf/filters/__init__.py
django_nlf/filters/base.py
django_nlf/filters/django.py
django_nlf/functions/__init__.py
django_nlf/functions/dates.py
django_nlf/functions/registry.py
django_nlf/rest_framework/__init__.py
django_nlf/rest_framework/backends.py
django_nlf/templates/django_nlf/rest_framework/form.html
django_nlf-0.0.4.dist-info/LICENSE
django_nlf-0.0.4.dist-info/METADATA
django_nlf-0.0.4.dist-info/WHEEL
django_nlf-0.0.4.dist-info/top_level.txt
django_nlf-0.0.4.dist-info/RECORD
