Metadata-Version: 2.1
Name: django-nlf
Version: 0.0.4
Summary: Django Natural Language Filter package
Home-page: https://github.com/hodossy/django-nlf
Author: Hodossy, Szabolcs
Author-email: hodossy.szabolcs@gmail.com
Maintainer: Hodossy, Szabolcs
Maintainer-email: hodossy.szabolcs@gmail.com
License: MIT
Keywords: django,natural-Language,filtering
Platform: any
Classifier: Development Status :: 4 - Beta
Classifier: Environment :: Web Environment
Classifier: Framework :: Django :: 2.2
Classifier: Framework :: Django :: 3.0
Classifier: Framework :: Django :: 3.1
Classifier: Framework :: Django
Classifier: Intended Audience :: Developers
Classifier: License :: OSI Approved :: MIT License
Classifier: Operating System :: OS Independent
Classifier: Programming Language :: Python
Classifier: Programming Language :: Python :: 3
Classifier: Programming Language :: Python :: 3.7
Classifier: Programming Language :: Python :: 3.8
Classifier: Programming Language :: Python :: 3.9
Classifier: Typing :: Typed
Requires-Python: >=3.7
Requires-Dist: antlr4-python3-runtime (==4.8)
Requires-Dist: django (>=2.2)
